arrtype/__init__.py
arrtype/__main__.py
arrtype/cli.py
arrtype/memory/__init__.py
arrtype/memory/properties.py
arrtype/memory/types.py
arrtype/type_dump.py
arrtype/type_tree.py
arrtype-0.1.1.dist-info/entry_points.txt
arrtype-0.1.1.dist-info/LICENSE
arrtype-0.1.1.dist-info/METADATA
arrtype-0.1.1.dist-info/WHEEL
arrtype-0.1.1.dist-info/RECORD
