Metadata-Version: 2.1
Name: arrtype
Version: 0.1.1
Summary: A type dumper for pirate101
Home-page: https://github.com/wizspoil/arrtype
License: MIT
Author: StarrFox
Author-email: starrfox6312@gmail.com
Requires-Python: >=3.11,<4.0
Classifier: License :: OSI Approved :: MIT License
Classifier: Programming Language :: Python :: 3
Classifier: Programming Language :: Python :: 3.11
Classifier: Programming Language :: Python :: 3.12
Classifier: Programming Language :: Python :: 3.13
Requires-Dist: click (>=8.2.1,<9.0.0)
Requires-Dist: iced-x86 (>=1.21.0,<2.0.0)
Requires-Dist: memobj (>=0.14.1,<0.15.0)
Project-URL: Repository, https://github.com/wizspoil/arrtype
